{
    "series": "Scope",
    "author": "blundetto",
    "tracks": [
        {
            "title": "13.00 - 16.00 SCOPE kurz",
            "artist": "Roland Widmer"
        },
        {
            "title": "I've Got to Have You",
            "artist": "Sheila Jack"
        },
        {
            "title": "Trouble",
            "artist": "Ray LaMontagne"
        },
        {
            "title": "Let the Sunshine In",
            "artist": "Galt MacDermot"
        },
        {
            "title": "STATION-ID - Andavoicepur",
            "artist": "Roland Widmer"
        },
        {
            "title": "Time Never Lies",
            "artist": "Sage"
        },
        {
            "title": "Breathe",
            "artist": "Brainstory"
        },
        {
            "title": "Nile Splash",
            "artist": "Never"
        },
        {
            "title": "STATION-ID - Anda Voice",
            "artist": "Roland Widmer"
        },
        {
            "title": "Holbox",
            "artist": "Simon Says"
        },
        {
            "title": "Super Lady",
            "artist": "Jeff Phelps"
        },
        {
            "title": "STATION-ID - Whisper",
            "artist": "Roland Widmer"
        },
        {
            "title": "If You Want Me to Stay",
            "artist": "Sly & The Family Stone"
        },
        {
            "title": "Book of the Month",
            "artist": "Nathaniel Merriweather"
        },
        {
            "title": "Stone",
            "artist": "Collard"
        },
        {
            "title": "13.00 - 16.00 SCOPE kurz",
            "artist": "Roland Widmer"
        },
        {
            "title": "I Hate I Walked Away",
            "artist": "Syl Johnson"
        },
        {
            "title": "Fever",
            "artist": "Robert Glasper"
        },
        {
            "title": "Hold Me Oh My Darling",
            "artist": "Marvin Gaye"
        },
        {
            "title": "STATION-ID - Doppeler",
            "artist": "Roland Widmer"
        },
        {
            "title": "Texas Sun",
            "artist": "Khruangbin"
        },
        {
            "title": "Home",
            "artist": "Caribou"
        },
        {
            "title": "Personal Jesus",
            "artist": "Johnny Cash"
        },
        {
            "title": "Some Velvet Morning",
            "artist": "Nancy Sinatra"
        },
        {
            "title": "13.00 - 16.00 SCOPE kurz",
            "artist": "Roland Widmer"
        },
        {
            "title": "Only Your Love",
            "artist": "Paul Kelly"
        },
        {
            "title": "Not Afraid, Part 2",
            "artist": "Mister Modo"
        },
        {
            "title": "STATION-ID - 5s Beep",
            "artist": "Roland Widmer"
        },
        {
            "title": "Sexy Sadie",
            "artist": "The Beatles"
        },
        {
            "title": "Claire",
            "artist": "Baxter Dury"
        },
        {
            "title": "La condition masculine",
            "artist": "Francis Bebey"
        },
        {
            "title": "Think (About It)",
            "artist": "Lyn Collins"
        },
        {
            "title": "STATION-ID - Andavoicepur",
            "artist": "Roland Widmer"
        },
        {
            "title": "Sitting Duck",
            "artist": "Gene Harris"
        },
        {
            "title": "Freedom",
            "artist": "Sampa The Great"
        },
        {
            "title": "The Ways",
            "artist": "Khalid"
        },
        {
            "title": "You Know You Like It",
            "artist": "AlunaGeorge"
        },
        {
            "title": "13.00 - 16.00 SCOPE kurz",
            "artist": "Roland Widmer"
        },
        {
            "title": "Coonshin",
            "artist": "Ayatollah"
        },
        {
            "title": "Deep Shadows",
            "artist": "Little Ann"
        },
        {
            "title": "Wish Someone Would Care",
            "artist": "Irma Thomas"
        },
        {
            "title": "STATION-ID - Whisper",
            "artist": "Roland Widmer"
        },
        {
            "title": "13.00 - 16.00 SCOPE kurz",
            "artist": "Roland Widmer"
        },
        {
            "title": "The Wolves",
            "artist": "Ben Howard"
        },
        {
            "title": "Hey Mami",
            "artist": "Sylvan Esso"
        },
        {
            "title": "STATION-ID - Doppeler",
            "artist": "Roland Widmer"
        },
        {
            "title": "Imitosis",
            "artist": "Andrew Bird"
        },
        {
            "title": "Failure",
            "artist": "Skinny"
        },
        {
            "title": "I've Had a Little Talk",
            "artist": "Horace Silver"
        },
        {
            "title": "STATION-ID - 5s Beep",
            "artist": "Roland Widmer"
        },
        {
            "title": "The Truth",
            "artist": "Handsome Boy Modeling School"
        },
        {
            "title": "Femme Fatale",
            "artist": "The Velvet Underground"
        },
        {
            "title": "13.00 - 16.00 SCOPE kurz",
            "artist": "Roland Widmer"
        },
        {
            "title": "Fu Manchu'",
            "artist": "Desmond Dekker"
        },
        {
            "title": "Mellow Mood",
            "artist": "Soul Sugar"
        },
        {
            "title": "Hell N Back",
            "artist": "Bakar"
        },
        {
            "title": "STATION-ID - 5s Beep",
            "artist": "Roland Widmer"
        },
        {
            "title": "Calaba Calabao",
            "artist": "La Tromba"
        },
        {
            "title": "Confessions",
            "artist": "Sudan Archives"
        },
        {
            "title": "2:53",
            "artist": "Misled Children"
        },
        {
            "title": "STATION-ID - Andavoicepur",
            "artist": "Roland Widmer"
        },
        {
            "title": "Ruler Of My Heart",
            "artist": "Irma Thomas"
        },
        {
            "title": "Tres equis",
            "artist": "Cypress Hill"
        },
        {
            "title": "Anyone Heard of a Donkey Punch?",
            "artist": "[no artist]"
        },
        {
            "title": "13.00 - 16.00 SCOPE kurz",
            "artist": "Roland Widmer"
        },
        {
            "title": "Beijos Seus Labios",
            "artist": "Baron Rétif & Concepción Perez"
        },
        {
            "title": "Benko",
            "artist": "Rocket Juice & The Moon"
        },
        {
            "title": "Irene",
            "artist": "Caribou"
        },
        {
            "title": "STATION-ID - Whisper",
            "artist": "Roland Widmer"
        },
        {
            "title": "Three Faces",
            "artist": "Menahan Street Band"
        },
        {
            "title": "LIFE SO HARD",
            "artist": "Aloe Blacc"
        },
        {
            "title": "4:52",
            "artist": "Misled Children"
        },
        {
            "title": "Legalize It",
            "artist": "Cypress Hill"
        },
        {
            "title": "D'Fish",
            "artist": "Chlorine Free"
        },
        {
            "title": "Gee Up",
            "artist": "Kindness"
        },
        {
            "title": "STATION-ID - Doppeler",
            "artist": "Roland Widmer"
        },
        {
            "title": "I Think It’s for the Feeling",
            "artist": "Al Green"
        },
        {
            "title": "13.00 - 16.00 SCOPE kurz",
            "artist": "Roland Widmer"
        },
        {
            "title": "La Horse (B.O.F. \"La Horse\")",
            "artist": "Serge Gainsbourg"
        },
        {
            "title": "King Solomon's Mines",
            "artist": "Native"
        },
        {
            "title": "Basta",
            "artist": "Souleance"
        },
        {
            "title": "STATION-ID - Whisper",
            "artist": "Roland Widmer"
        },
        {
            "title": "Love Won’t Come Easy",
            "artist": "The Heptones"
        },
        {
            "title": "STATION-ID - 5s Beep",
            "artist": "Roland Widmer"
        },
        {
            "title": "Selfish",
            "artist": "Jordan Rakei"
        },
        {
            "title": "STATION-ID - Whisper",
            "artist": "Roland Widmer"
        },
        {
            "title": "Suspense",
            "artist": "La Funk Mob"
        },
        {
            "title": "What Is This Thing Called Love",
            "artist": "The Hep Chaps"
        },
        {
            "title": "Whose Head Are You After?",
            "artist": "Michel Legrand"
        },
        {
            "title": "Fireworks",
            "artist": "Original Memphis Five"
        },
        {
            "title": "STATION-ID - Andavoicepur",
            "artist": "Roland Widmer"
        },
        {
            "title": "STATION-ID - Duet mit Büchsen",
            "artist": "Roland Widmer"
        },
        {
            "title": "La Cumparsita",
            "artist": "Carlo Molina's Tango Orchestra"
        },
        {
            "title": "Lament 1 'Bird's Lament'",
            "artist": "Moondog"
        },
        {
            "title": "Let It Come Down",
            "artist": "Nick Waterhouse"
        },
        {
            "title": "You Don't Own Me",
            "artist": "Lesley Gore"
        },
        {
            "title": "STATION-ID - Whisper",
            "artist": "Roland Widmer"
        },
        {
            "title": "Ana Na Ming (La Funk Mob Remix)",
            "artist": "Salif Keita"
        },
        {
            "title": "Maloya ton tisane",
            "artist": "Commandant Cad...e La Fournaise"
        },
        {
            "title": "The Donkey",
            "artist": "The Poets of Rhythm"
        },
        {
            "title": "Carta ao Tom 74",
            "artist": "Vinicius de Moraes"
        },
        {
            "title": "STATION-ID - Doppeler",
            "artist": "Roland Widmer"
        },
        {
            "title": "The Ember Song",
            "artist": "Sidney Barnes"
        },
        {
            "title": "Fragile",
            "artist": "Tech N9ne"
        },
        {
            "title": "STATION-ID - Wusch",
            "artist": "Roland Widmer"
        },
        {
            "title": "River",
            "artist": "Ibeyi"
        },
        {
            "title": "Man O To",
            "artist": "Nu"
        },
        {
            "title": "Kendrick (Too Hot Outside Edit)",
            "artist": "Anushka"
        },
        {
            "title": "STATION-ID - Fro electronic",
            "artist": "Roland Widmer"
        },
        {
            "title": "Dia Real De Um Sonho Comum",
            "artist": "Leonardo Marques"
        },
        {
            "title": "Menina mulher da pele preta",
            "artist": "Jorge Ben"
        },
        {
            "title": "STATION-ID - Cutter",
            "artist": "Roland Widmer"
        },
        {
            "title": "Pulsion",
            "artist": "Jacques Loussier"
        }
    ]
}